crocodeel/__init__.py
crocodeel/ab_table_utils.py
crocodeel/common.py
crocodeel/conta_event.py
crocodeel/crocodeel.py
crocodeel/execution_description.py
crocodeel/models/crocodeel_rf_Mar2023.joblib
crocodeel/plot_conta.py
crocodeel/search_conta.py
crocodeel/test_data/mgs_profiles_test.tsv
crocodeel/test_data/results/contamination_events.pdf
crocodeel/test_data/results/contamination_events.tsv
crocodeel/test_install.py
crocodeel/train_model.py
crocodeel-1.0.7.dist-info/COPYING
crocodeel-1.0.7.dist-info/METADATA
crocodeel-1.0.7.dist-info/WHEEL
crocodeel-1.0.7.dist-info/entry_points.txt
crocodeel-1.0.7.dist-info/RECORD
