Metadata-Version: 2.3
Name: crocodeel
Version: 1.0.7
Summary: CroCoDeEL is a tool that detects cross-sample (aka well-to-well) contamination in shotgun metagenomic data
License: GPL-3.0-or-later
Keywords: Metagenomics
Author: Lindsay Goulet
Author-email: lindsay.goulet@inrae.fr
Requires-Python: >=3.12
Classifier: Environment :: Console
Classifier: Intended Audience :: Science/Research
Classifier: License :: OSI Approved :: GNU General Public License v3 or later (GPLv3+)
Classifier: Operating System :: OS Independent
Classifier: Programming Language :: Python :: 3
Classifier: Programming Language :: Python :: 3.12
Classifier: Programming Language :: Python :: 3.13
Classifier: Topic :: Scientific/Engineering :: Bio-Informatics
Requires-Dist: joblib (>=1.4,<2.0)
Requires-Dist: matplotlib (>=3.8,<4.0)
Requires-Dist: numpy (>=1.26,<2.0)
Requires-Dist: pandas (>=2.2,<3.0)
Requires-Dist: scikit-learn (>=1.3,<1.4)
Requires-Dist: scipy (>=1.13,<2.0)
Requires-Dist: tqdm (>=4.66,<5.0)
Project-URL: Repository, https://github.com/metagenopolis/CroCoDeEL
